bioio_base/__init__.py
bioio_base/benchmark.py
bioio_base/constants.py
bioio_base/dimensions.py
bioio_base/exceptions.py
bioio_base/image_container.py
bioio_base/io.py
bioio_base/noop_reader.py
bioio_base/py.typed
bioio_base/reader.py
bioio_base/reader_metadata.py
bioio_base/standard_metadata.py
bioio_base/test_utilities.py
bioio_base/transforms.py
bioio_base/types.py
bioio_base/writer.py
bioio_base/tests/__init__.py
bioio_base/tests/conftest.py
bioio_base/tests/test_benchmark.py
bioio_base/tests/test_dimensions.py
bioio_base/tests/test_io.py
bioio_base/tests/test_standard_metadata.py
bioio_base/tests/test_transforms.py
bioio_base/tests/resources/sample.ome.json
bioio_base/tests/resources/sample_timelapse.ome.json
bioio_base/tests/resources/sample_timelapse_20_sec_interval.json
bioio_base-3.2.0.dist-info/licenses/LICENSE
docs/conf.py
docs/contributing.rst
docs/index.rst
docs/installation.rst
bioio_base-3.2.0.dist-info/METADATA
bioio_base-3.2.0.dist-info/WHEEL
bioio_base-3.2.0.dist-info/top_level.txt
bioio_base-3.2.0.dist-info/RECORD
