Metadata-Version: 2.4
Name: bioio-base
Version: 3.2.0
Summary: Typing, base classes, and more for BioIO projects.
Author-email: Eva Maxfield Brown <evamaxfieldbrown@gmail.com>, Dan Toloudis <danielt@alleninstitute.org>
License: BSD License
Project-URL: Homepage, https://github.com/bioio-devs/bioio-base
Project-URL: Bug Tracker, https://github.com/bioio-devs/bioio-base/issues
Project-URL: Documentation, https://bioio-devs.github.io/bioio-base
Project-URL: User Support, https://github.com/bioio-devs/bioio-base/issues
Classifier: Development Status :: 4 - Beta
Classifier: Natural Language :: English
Classifier: Programming Language :: Python :: 3.10
Classifier: Programming Language :: Python :: 3.11
Classifier: Programming Language :: Python :: 3.12
Classifier: Programming Language :: Python :: 3.13
Requires-Python: >=3.10
License-File: LICENSE
Requires-Dist: dask[array,distributed]!=2022.5.1,>=2021.4.1
Requires-Dist: fsspec!=2022.7.0,>=2021.4.0
Requires-Dist: numpy>=1.21.0
Requires-Dist: ome-types[pint]>=0.2
Requires-Dist: pint
Requires-Dist: xarray>=2022.6.0
Provides-Extra: lint
Requires-Dist: pre-commit>=2.20.0; extra == "lint"
Provides-Extra: test
Requires-Dist: coverage>=5.1; extra == "test"
Requires-Dist: pytest>=5.4.3; extra == "test"
Requires-Dist: pytest-cov>=2.9.0; extra == "test"
Requires-Dist: pytest-raises>=0.11; extra == "test"
Requires-Dist: aiohttp; extra == "test"
Requires-Dist: requests; extra == "test"
Provides-Extra: docs
Requires-Dist: m2r2>=0.2.7; extra == "docs"
Requires-Dist: Sphinx>=4.0.0; extra == "docs"
Requires-Dist: furo>=2022.4.7; extra == "docs"
Requires-Dist: numpydoc; extra == "docs"
Requires-Dist: sphinx-copybutton; extra == "docs"
Requires-Dist: docutils<0.19,>=0.18; extra == "docs"
Provides-Extra: dev
Requires-Dist: ipython>=8.4.0; extra == "dev"
Dynamic: license-file
